github_contents.py
github_contents-0.2.dist-info/METADATA
github_contents-0.2.dist-info/WHEEL
github_contents-0.2.dist-info/top_level.txt
github_contents-0.2.dist-info/RECORD
