Metadata-Version: 2.1
Name: github-contents
Version: 0.2
Summary: Python class for reading and writing data to a GitHub repository
Home-page: https://github.com/simonw/github-contents
Author: Simon Willison
License: Apache License, Version 2.0
Project-URL: Issues, https://github.com/simonw/github-contents/issues
Project-URL: CI, https://github.com/simonw/github-contents/actions
Project-URL: Changelog, https://github.com/simonw/github-contents/releases
Platform: UNKNOWN
Requires-Dist: requests
Provides-Extra: test
Requires-Dist: pytest ; extra == 'test'
Requires-Dist: betamax ; extra == 'test'
